writeadoc/__init__.py
writeadoc/autodoc.py
writeadoc/cli.py
writeadoc/exceptions.py
writeadoc/main.py
writeadoc/pages.py
writeadoc/search.py
writeadoc/types.py
writeadoc/utils.py
writeadoc/blueprint/docs.py
writeadoc/blueprint/assets/css/base.css
writeadoc/blueprint/assets/css/custom.css
writeadoc/blueprint/assets/css/layout.css
writeadoc/blueprint/assets/fonts/Inter-LICENSE.txt
writeadoc/blueprint/assets/fonts/Inter-Variable.woff2
writeadoc/blueprint/assets/images/apple-touch-icon.png
writeadoc/blueprint/assets/images/favicon.png
writeadoc/blueprint/assets/images/favicon.svg
writeadoc/blueprint/assets/images/opengraph.png
writeadoc/blueprint/assets/js/code.js
writeadoc/blueprint/assets/js/color-scheme.js
writeadoc/blueprint/assets/js/lunr.da.min.js
writeadoc/blueprint/assets/js/lunr.de.min.js
writeadoc/blueprint/assets/js/lunr.es.min.js
writeadoc/blueprint/assets/js/lunr.fr.min.js
writeadoc/blueprint/assets/js/lunr.it.min.js
writeadoc/blueprint/assets/js/lunr.min.js
writeadoc/blueprint/assets/js/lunr.pt.min.js
writeadoc/blueprint/assets/js/page.js
writeadoc/blueprint/assets/js/script.js
writeadoc/blueprint/assets/js/search.js
writeadoc/blueprint/assets/js/turbo.min.js
writeadoc/blueprint/content/index.md
writeadoc/blueprint/content/welcome.md
writeadoc/blueprint/views/autodoc.md.jinja
writeadoc/blueprint/views/banner_archived.jinja
writeadoc/blueprint/views/color_scheme.jinja
writeadoc/blueprint/views/footer.jinja
writeadoc/blueprint/views/header.jinja
writeadoc/blueprint/views/index.jinja
writeadoc/blueprint/views/language_selector.jinja
writeadoc/blueprint/views/layout.jinja
writeadoc/blueprint/views/llm.jinja
writeadoc/blueprint/views/metadata.jinja
writeadoc/blueprint/views/page.jinja
writeadoc/blueprint/views/page_nav.jinja
writeadoc/blueprint/views/page_pager.jinja
writeadoc/blueprint/views/page_toc.jinja
writeadoc/blueprint/views/robots.txt.jinja
writeadoc/blueprint/views/search.jinja
writeadoc/blueprint/views/sidebar.jinja
writeadoc-0.13.0.dist-info/METADATA
writeadoc-0.13.0.dist-info/WHEEL
writeadoc-0.13.0.dist-info/entry_points.txt
writeadoc-0.13.0.dist-info/top_level.txt
writeadoc-0.13.0.dist-info/RECORD
