Metadata-Version: 2.4
Name: writeadoc
Version: 0.13.0
Summary: Focus on your content and let WriteADoc take care of the rest
Author-email: Juan Pablo Scaletti <juanpablo@jpscaletti.com>
Project-URL: Homepage, https://writeadoc.scaletti.dev/
Project-URL: GitHub, https://github.com/jpsca/writeadoc
Requires-Python: >=3.12
Requires-Dist: docstring-parser>=0.17.0
Requires-Dist: hecto>=2.0.1
Requires-Dist: jinja2>=3.1.6
Requires-Dist: jx>=0.3.0
Requires-Dist: mistune>=3.2.0
Requires-Dist: pygments>=2.19.2
Requires-Dist: strictyaml>=1.7.3
Requires-Dist: ty>=0.0.1a15
Requires-Dist: watchdog>=6.0.0
